acuimax/AcuiMax.py
acuimax/AcuiMaxModulo.py
acuimax/__init__.py
acuimax-0.1.3.dist-info/LICENSE
acuimax-0.1.3.dist-info/METADATA
acuimax-0.1.3.dist-info/WHEEL
acuimax-0.1.3.dist-info/top_level.txt
acuimax-0.1.3.dist-info/RECORD
