Metadata-Version: 2.1
Name: acuimax
Version: 0.1.3
Summary: CAPACIDAD DE CARGA MÁXIMA Y TIEMPO DE AGOTAMIENTO ENTRE DOS ACUÍFEROS.
Home-page: https://github.com/JonathanTapia-1/AcuiMax.git
Author: Ajila Nagua Ana Isabel, Ordoñez Salinas Xavi Alexander, Jonathan Tapia Cuenca, Taipe Jaramillo Josselyn Estefania
Author-email: xavial152001@gmail.com, aiajila@utpl.edu.ec, jetaipe@utpl.edu.ec, jatapia14@utpl.edu.ec 
License: UNKNOWN
Platform: UNKNOWN
Classifier: Programming Language :: Python :: 3
Classifier: License :: OSI Approved :: MIT License
Classifier: Operating System :: OS Independent
Requires-Python: >=3.6
License-File: LICENSE
Requires-Dist: numpy ==1.24.1
